odoo/addons/printing_auto_stock_picking/README.rst
odoo/addons/printing_auto_stock_picking/__init__.py
odoo/addons/printing_auto_stock_picking/__manifest__.py
odoo/addons/printing_auto_stock_picking/i18n/it.po
odoo/addons/printing_auto_stock_picking/i18n/printing_auto_stock_picking.pot
odoo/addons/printing_auto_stock_picking/models/__init__.py
odoo/addons/printing_auto_stock_picking/models/stock_picking.py
odoo/addons/printing_auto_stock_picking/models/stock_picking_type.py
odoo/addons/printing_auto_stock_picking/readme/CONFIGURE.md
odoo/addons/printing_auto_stock_picking/readme/CONTRIBUTORS.md
odoo/addons/printing_auto_stock_picking/readme/DESCRIPTION.md
odoo/addons/printing_auto_stock_picking/security/ir.model.access.csv
odoo/addons/printing_auto_stock_picking/security/ir_rule.xml
odoo/addons/printing_auto_stock_picking/static/description/icon.png
odoo/addons/printing_auto_stock_picking/static/description/index.html
odoo/addons/printing_auto_stock_picking/tests/__init__.py
odoo/addons/printing_auto_stock_picking/tests/test_printing_auto_stock.py
odoo/addons/printing_auto_stock_picking/views/stock_picking.xml
odoo/addons/printing_auto_stock_picking/views/stock_picking_type.xml
odoo_addon_printing_auto_stock_picking-18.0.1.0.1.1.dist-info/METADATA
odoo_addon_printing_auto_stock_picking-18.0.1.0.1.1.dist-info/WHEEL
odoo_addon_printing_auto_stock_picking-18.0.1.0.1.1.dist-info/top_level.txt
odoo_addon_printing_auto_stock_picking-18.0.1.0.1.1.dist-info/RECORD
